aronet-0.1b1.dist-info/METADATA
aronet-0.1b1.dist-info/WHEEL
aronet-0.1b1.dist-info/entry_points.txt
aronet/libexec/charon
aronet/libexec/swanctl
aronet/libexec/bird
aronet/libexec/birdcl
aronet/__init__.py
aronet/main.py
aronet/config.py
aronet/util.py
aronet/netlink.py
aronet/cmd/__init__.py
aronet/cmd/base.py
aronet/cmd/daemon.py
aronet/cmd/load.py
aronet/cmd/birdc.py
aronet/cmd/swanctl.py
aronet/daemon/__init__.py
aronet/daemon/strongswan.py
aronet/daemon/backend.py
aronet/daemon/bird.py
aronet/strongswan/__init__.py
aronet/strongswan/client.py
aronet/libexec/updown.sh
vici/__init__.py
vici/command_wrappers.py
vici/exception.py
vici/protocol.py
vici/session.py
aronet-0.1b1.dist-info/RECORD
