Metadata-Version: 2.1
Name: aronet
Version: 0.1b1
Summary: Auto routed full mesh overlay networks.
Classifier: Development Status :: 3 - Alpha
Classifier: Programming Language :: Python
Project-URL: Homepage, https://github.com/RMTT/aronet
Project-URL: Repository, https://github.com/RMTT/aronet.git
Requires-Python: >=3.10
Requires-Dist: cryptography
Requires-Dist: pyroute2
Requires-Dist: jsonschema
